{
  "version": "1.0.0",
  "name": "cinematic-styles-directors-robert-eggers",
  "displayName": "Robert Eggers Style Guide",
  "description": "Screenplay style guide for Robert Eggers",
  "type": "writing-standards",
  "tags": [
    "screenplay",
    "cinematic-style",
    "director",
    "auteur",
    "robert-eggers"
  ],
  "compatibility": {
    "augmentMinVersion": "1.0.0",
    "nodeMinVersion": "18.0.0"
  },
  "characterCount": 5000,
  "lastUpdated": "2026-02-25",
  "files": {
    "rules": "robert-eggers.md",
    "examples": []
  }
}
